ndex/__init__.py
ndex/client.py
ndex/create_aspect.py
ndex/ndexGraphBuilder.py
ndex/networkn.py
ndex/beta/__init__.py
ndex/beta/layouts.py
ndex/beta/path_scoring.py
ndex/beta/toolbox.py
ndex/beta/test/__init__.py
ndex/beta/test/betascratchtests.py
ndex/beta/test/loadexample.txt
ndex/beta/test/loadsmallexample.txt
ndex/beta/test/small_annotate.txt
ndex/beta/test/st_layout_annotate1.txt
ndex/beta/test/st_layout_annotate2.txt
ndex/beta/test/st_layout_network1.txt
ndex/beta/test/st_layout_network2.txt
ndex/test/A549-SL-network.cx
ndex/test/The_RAS_Machine.cx
ndex/test/__init__.py
ndex/test/filtered.cx
ndex/test/non_unittest_testing.py
ndex/test/scratch_test_networkn.py
ndex/test/scratchtests.py
ndex/test/small_corpus.cx
ndex/test/test.txt
ndex/test/test_NdexClient.py
ndex/test/test_NetworkNConstructor.py
ndex/test/test_ProvenanceAndProfile.py
ndex/test/test_UpdatingNsetProperty.py
ndex/test/test_network.py
ndex/test/test_networkn.py
ndex/test/test_properties.py
ndex/test/test_query.py
ndex/test/test_setting_visibility.py
ndex/test/test_system_properties.py
ndex/test/test_user.py
ndex/test/tiny_corpus.cx
ndex/test/tiny_network.cx
ndex-3.0.11.23.dist-info/DESCRIPTION.rst
ndex-3.0.11.23.dist-info/METADATA
ndex-3.0.11.23.dist-info/RECORD
ndex-3.0.11.23.dist-info/WHEEL
ndex-3.0.11.23.dist-info/metadata.json
ndex-3.0.11.23.dist-info/top_level.txt
